reverso_api/__init__.py
reverso_api/context.py
reverso_api/voice.py
tests/__init__.py
tests/voice.py
Reverso_API-0.0.1b3.dist-info/LICENSE
Reverso_API-0.0.1b3.dist-info/METADATA
Reverso_API-0.0.1b3.dist-info/WHEEL
Reverso_API-0.0.1b3.dist-info/top_level.txt
Reverso_API-0.0.1b3.dist-info/RECORD
