Metadata-Version: 2.1
Name: Reverso_API
Version: 0.0.1b3
Summary: Reverso.net API for Python
Home-page: https://github.com/demian-wolf/ReversoAPI
Author: Demian Wolf
Author-email: demianwolfssd@gmail.com
License: MIT
Download-URL: https://github.com/demian-wolf/ReversoAPI/archive/v0.0.1.beta.3.tar.gz
Keywords: REVERSO,REVERSO-CONTEXT,REVERSO CONTEXT,CONTEXT,REVERSO-VOICE,REVERSO VOICE,VOICE,REVERSO-API,API,WRAPPER,PYTHON
Platform: UNKNOWN
Classifier: Programming Language :: Python :: 3
Classifier: License :: OSI Approved :: MIT License
Classifier: Operating System :: OS Independent
Classifier: Development Status :: 4 - Beta
Classifier: Intended Audience :: Developers
Provides-Extra: playing spoken text instead of just getting its MP3 data and/or saving it to file-like objects
